aurorawatchuk/snapshot.py
aurorawatchuk/__init__.py
aurorawatchuk-0.2.2.dist-info/DESCRIPTION.rst
aurorawatchuk-0.2.2.dist-info/metadata.json
aurorawatchuk-0.2.2.dist-info/METADATA
aurorawatchuk-0.2.2.dist-info/top_level.txt
aurorawatchuk-0.2.2.dist-info/WHEEL
aurorawatchuk-0.2.2.dist-info/RECORD
